PyTCI/__init__.py
PyTCI/models/__init__.py
PyTCI/models/alfentanil.py
PyTCI/models/base.py
PyTCI/models/dexmedetomidine.py
PyTCI/models/propofol.py
PyTCI/models/remifentanil.py
PyTCI/weights/__init__.py
PyTCI/weights/leanbodymass.py
tests/__init__.py
tests/test_alfentanil.py
tests/test_dexmedetomidine.py
tests/test_infusions.py
tests/test_lbm.py
tests/test_propofol.py
tests/test_remifentanil.py
PyTCI-1.1.dist-info/METADATA
PyTCI-1.1.dist-info/WHEEL
PyTCI-1.1.dist-info/top_level.txt
PyTCI-1.1.dist-info/RECORD
