Metadata-Version: 2.1
Name: PyTCI
Version: 1.1
Summary: A package for target controlled infusions
Home-page: https://github.com/JMathiszig-Lee/PyTCI
Author: Jakob Mathiszig-Lee
Author-email: jakob@mathisziglee.co.uk
License: UNKNOWN
Platform: UNKNOWN
Classifier: Programming Language :: Python :: 3.6
Classifier: Programming Language :: Python :: 3.7
Classifier: Programming Language :: Python :: 3.8
Classifier: License :: OSI Approved :: MIT License
Classifier: Operating System :: OS Independent
